soda/__main__.py
soda/__version__.py
soda/scan.py
soda/cli/cli.py
soda/cloud/dbt_config.py
soda/common/aws_credentials.py
soda/common/config_helper.py
soda/common/exception_helper.py
soda/common/exceptions.py
soda/common/file_system.py
soda/common/jinja.py
soda/common/json_helper.py
soda/common/lazy.py
soda/common/log.py
soda/common/logs.py
soda/common/parser.py
soda/common/query_helper.py
soda/common/random_helper.py
soda/common/string_helper.py
soda/common/undefined_instance.py
soda/common/yaml_helper.py
soda/configuration/configuration.py
soda/configuration/configuration_parser.py
soda/execution/check_outcome.py
soda/execution/column.py
soda/execution/data_source.py
soda/execution/data_source_manager.py
soda/execution/data_source_scan.py
soda/execution/data_type.py
soda/execution/derived_formula.py
soda/execution/identity.py
soda/execution/partition.py
soda/execution/schema_comparator.py
soda/execution/table.py
soda/execution/telemetry.py
soda/execution/check/anomaly_metric_check.py
soda/execution/check/automated_monitoring_run.py
soda/execution/check/change_over_time_metric_check.py
soda/execution/check/check.py
soda/execution/check/discover_tables_run.py
soda/execution/check/distribution_check.py
soda/execution/check/freshness_check.py
soda/execution/check/metric_check.py
soda/execution/check/profile_columns_run.py
soda/execution/check/reference_check.py
soda/execution/check/row_count_comparison_check.py
soda/execution/check/sample_tables_run.py
soda/execution/check/schema_check.py
soda/execution/check/user_defined_failed_rows_check.py
soda/execution/check/user_defined_failed_rows_expression_check.py
soda/execution/metric/column_metrics.py
soda/execution/metric/derived_metric.py
soda/execution/metric/metric.py
soda/execution/metric/numeric_query_metric.py
soda/execution/metric/query_metric.py
soda/execution/metric/reference_metric.py
soda/execution/metric/schema_metric.py
soda/execution/metric/user_defined_failed_rows_metric.py
phiture_soda_core-3.0.14.1.dist-info/METADATA
phiture_soda_core-3.0.14.1.dist-info/WHEEL
phiture_soda_core-3.0.14.1.dist-info/entry_points.txt
phiture_soda_core-3.0.14.1.dist-info/top_level.txt
phiture_soda_core-3.0.14.1.dist-info/RECORD
