Metadata-Version: 2.1
Name: phiture-soda-core
Version: 3.0.14.1
Summary: Soda Core library & CLI
Author: Soda Data N.V.
Author-email: info@soda.io
Classifier: Development Status :: 4 - Beta
Classifier: License :: OSI Approved :: Apache Software License
Classifier: Operating System :: Microsoft :: Windows
Classifier: Operating System :: MacOS :: MacOS X
Classifier: Operating System :: POSIX :: Linux
Classifier: Programming Language :: Python :: 3.8
Classifier: Programming Language :: Python :: 3.9
Classifier: Programming Language :: Python :: 3.10
Requires-Python: >=3.7
Requires-Dist: markupsafe (==2.0.1)
Requires-Dist: Jinja2 (~=2.11)
Requires-Dist: click (~=8.0)
Requires-Dist: ruamel.yaml (~=0.17.21)
Requires-Dist: requests (>=2.27.1)
Requires-Dist: antlr4-python3-runtime (~=4.11.1)
Requires-Dist: opentelemetry-api (~=1.11.0)
Requires-Dist: opentelemetry-exporter-otlp-proto-http (~=1.11.0)
Requires-Dist: protobuf (>=3.20.0)
Requires-Dist: sqlparse (~=0.4)
